{
    "actionOnStepFail": "stop", 
    "concurrency": 1, 
    "enabled": true, 
    "externalUuid4": "aeced3e6-b3d5-4ce5-8b81-83521128170a", 
    "isBlueprint": true, 
    "key": "deploywindowsvmfromtemplateonmacosorlinuxworker", 
    "links": [
        {
            "stepKey": "listcustomisationspeconmacosorlinuxworker"
        }, 
        {
            "stepKey": "deletevmwithmacosorlinuxworker"
        }, 
        {
            "stepKey": "createwindowsvmfromtemplatewithmacosorlinuxworker"
        }, 
        {
            "stepKey": "startvmwithmacosorlinuxworker"
        }
    ], 
    "name": "Deploy Windows VM From Template on macOS or Linux Worker", 
    "type": "com.servertribe.attune.tuples.StepGroupTuple"
}